aind_dispim_processing/__init__.py
aind_dispim_processing/converter_capsule.py
aind_dispim_processing/logging_capsule.py
aind_dispim_processing/registration_capsule.py
aind_dispim_processing-0.0.3.dist-info/LICENSE
aind_dispim_processing-0.0.3.dist-info/METADATA
aind_dispim_processing-0.0.3.dist-info/WHEEL
aind_dispim_processing-0.0.3.dist-info/top_level.txt
aind_dispim_processing-0.0.3.dist-info/RECORD
