Metadata-Version: 2.1
Name: aind-dispim-processing
Version: 0.0.3
Summary: Library for Dispim Code Ocean Pipeline
Author: Allen Institute for Neural Dynamics
License: MIT
Classifier: Programming Language :: Python :: 3
Requires-Python: >=3.7
License-File: LICENSE
Requires-Dist: argschema
Requires-Dist: aind-data-transfer
Requires-Dist: aind-ng-link
Requires-Dist: psutil
Provides-Extra: dev
Requires-Dist: black ; extra == 'dev'
Requires-Dist: coverage ; extra == 'dev'
Requires-Dist: flake8 ; extra == 'dev'
Requires-Dist: interrogate ; extra == 'dev'
Requires-Dist: isort ; extra == 'dev'
Requires-Dist: Sphinx ; extra == 'dev'
Requires-Dist: furo ; extra == 'dev'
